brainly_api/__init__.py
brainly_api/constants/__init__.py
brainly_api/constants/defaults.py
brainly_api/constants/markets.py
brainly_api/graphql_api/__init__.py
brainly_api/graphql_api/exceptions.py
brainly_api/graphql_api/graphql_api.py
brainly_api/graphql_api/graphql_queries/__init__.py
brainly_api/graphql_api/graphql_queries/GetUser.graphql
brainly_api/graphql_api/graphql_queries/GetUser.py
brainly_api/graphql_api/graphql_queries/graphql.config.yml
brainly_api/graphql_api/graphql_utils.py
brainly_api/graphql_api/responses.py
brainly_api/legacy_api/__init__.py
brainly_api/legacy_api/entities.py
brainly_api/legacy_api/exceptions.py
brainly_api/legacy_api/legacy_api.py
brainly_api/legacy_api/responses.py
brainly_api-0.1.1.dist-info/LICENSE
brainly_api-0.1.1.dist-info/METADATA
brainly_api-0.1.1.dist-info/WHEEL
brainly_api-0.1.1.dist-info/RECORD
