Metadata-Version: 2.1
Name: brainly-api
Version: 0.1.1
Summary: The ultimate HTTP library designed to communicate with the Brainly APIs
Home-page: https://github.com/vlaex/brainly-api-python
License: MIT
Keywords: api,brainly,brainly api,znanija,nosdevoirs,brainly.com,znanija.com
Author: vlaex
Requires-Python: >=3.11,<4.0
Classifier: Development Status :: 1 - Planning
Classifier: Environment :: Web Environment
Classifier: Intended Audience :: Developers
Classifier: License :: OSI Approved :: MIT License
Classifier: Operating System :: OS Independent
Classifier: Programming Language :: Python :: 3
Classifier: Programming Language :: Python :: 3.11
Classifier: Programming Language :: Python :: 3.12
Classifier: Topic :: Software Development :: Libraries :: Python Modules
Requires-Dist: httpx[http2] (>=0.27.0,<0.28.0)
Project-URL: Repository, https://github.com/vlaex/brainly-api-python
